<?xml version="1.0" standalone="yes"?>  <DATAPACKET Version="2.0"><METADATA><FIELDS><FIELD attrname="ALIQUOTA" fieldtype="string" WIDTH="10"/><FIELD attrname="VALOR" fieldtype="string" WIDTH="5"/><FIELD attrname="NUM_SERIE" fieldtype="string" WIDTH="20"/></FIELDS><PARAMS CHANGE_LOG="1 0 4 2 0 4 3 0 4 4 0 4 5 0 4 6 0 4 7 0 4 8 0 4 9 0 4 10 0 4 11 0 4 12 0 4 13 0 4 14 0 4 15 0 4 16 0 4 17 0 4 18 0 4"/></METADATA><ROWDATA><ROW RowState="4" ALIQUOTA="1TDesc" VALOR="Desco" NUM_SERIE="EMULADOR"/><ROW RowState="4" ALIQUOTA="2TDesc" VALOR="Desco" NUM_SERIE="EMULADOR"/><ROW RowState="4" ALIQUOTA="3T0000" VALOR="0000" NUM_SERIE="EMULADOR"/><ROW RowState="4" ALIQUOTA="4T0000" VALOR="0000" NUM_SERIE="EMULADOR"/><ROW RowState="4" ALIQUOTA="5T0000" VALOR="0000" NUM_SERIE="EMULADOR"/><ROW RowState="4" ALIQUOTA="6T0000" VALOR="0000" NUM_SERIE="EMULADOR"/><ROW RowState="4" ALIQUOTA="7T0000" VALOR="0000" NUM_SERIE="EMULADOR"/><ROW RowState="4" ALIQUOTA="8T0000" VALOR="0000" NUM_SERIE="EMULADOR"/><ROW RowState="4" ALIQUOTA="9T0000" VALOR="0000" NUM_SERIE="EMULADOR"/><ROW RowState="4" ALIQUOTA="10T0000" VALOR="0000" NUM_SERIE="EMULADOR"/><ROW RowState="4" ALIQUOTA="11T0000" VALOR="0000" NUM_SERIE="EMULADOR"/><ROW RowState="4" ALIQUOTA="12T0000" VALOR="0000" NUM_SERIE="EMULADOR"/><ROW RowState="4" ALIQUOTA="13T0000" VALOR="0000" NUM_SERIE="EMULADOR"/><ROW RowState="4" ALIQUOTA="14T0000" VALOR="0000" NUM_SERIE="EMULADOR"/><ROW RowState="4" ALIQUOTA="15T0000" VALOR="0000" NUM_SERIE="EMULADOR"/><ROW RowState="4" ALIQUOTA="16T0000" VALOR="0000" NUM_SERIE="EMULADOR"/><ROW RowState="4" ALIQUOTA="17T0000" VALOR="0000" NUM_SERIE="EMULADOR"/><ROW RowState="4" ALIQUOTA="18TISSQ" VALOR="ISSQN" NUM_SERIE="EMULADOR"/></ROWDATA></DATAPACKET>