<?xml version="1.0" standalone="yes"?>  <DATAPACKET Version="2.0"><METADATA><FIELDS><FIELD attrname="CODIGO" fieldtype="i4" required="true"/><FIELD attrname="NOME" fieldtype="string" required="true" WIDTH="50"/><FIELD attrname="NOME_FANTASIA" fieldtype="string" WIDTH="60"/><FIELD attrname="ENDERECO" fieldtype="string" WIDTH="50"/><FIELD attrname="BAIRRO" fieldtype="string" WIDTH="30"/><FIELD attrname="CODCIDADE" fieldtype="i4"/><FIELD attrname="CEP" fieldtype="string" WIDTH="15"/><FIELD attrname="UF" fieldtype="string" WIDTH="2"/><FIELD attrname="CPF" fieldtype="string" WIDTH="15"/><FIELD attrname="RG" fieldtype="string" WIDTH="20"/><FIELD attrname="CGC" fieldtype="string" WIDTH="20"/><FIELD attrname="IE" fieldtype="string" WIDTH="20"/><FIELD attrname="TELEFONE" fieldtype="string" WIDTH="16"/><FIELD attrname="CELULAR" fieldtype="string" WIDTH="16"/><FIELD attrname="INATIVO" fieldtype="string" WIDTH="1"/><FIELD attrname="NOME_CIDADE" fieldtype="string" WIDTH="50"/></FIELDS><PARAMS LCID="0"/></METADATA><ROWDATA><ROW CODIGO="1" NOME="CONSUMIDOR FINAL" ENDERECO="ESTABELICIMENTO DO EMITENTE" CODCIDADE="1" CEP="79740-000" UF="MS" CPF="542.839.061-15" INATIVO="N" NOME_CIDADE="IVINHEMA"/><ROW CODIGO="2" NOME="DARI AGOSTINHO VARINI JUNIOR" ENDERECO="RUA: PROF.MAURO DA SILVA, 338" CODCIDADE="1" CEP="79740-000" UF="MS" CPF="922.005.591-00" RG="1267999" TELEFONE="3442-4972" CELULAR="9985-8738" INATIVO="N" NOME_CIDADE="IVINHEMA"/><ROW CODIGO="3" NOME="AMANDA DOS SANTOS TERUEL VARINI" ENDERECO="RUA: MARTINS LEVI, 338" CODCIDADE="1" CEP="79740-000" UF="MS" CPF="003.827.881-25" RG="1693914" TELEFONE="3442-4972" CELULAR="9939-9958" INATIVO="N" NOME_CIDADE="IVINHEMA"/><ROW CODIGO="4" NOME="BP SOLUTIONS LTDA" NOME_FANTASIA="BP SOLUTIONS" ENDERECO="AV LIBERDADE, 00809" CODCIDADE="4" CEP="01503-001" UF="SP" CGC="02.911.224/0001-80" IE="115204814110" TELEFONE="11-3388-7700" INATIVO="N" NOME_CIDADE="SAO PAULO"/></ROWDATA></DATAPACKET>